{
  "player": {
    "player_id": "8142c9cd-ddc5-47a4-b58c-78af1079ee2c",
    "name": "Kyle Teel",
    "position": "C",
    "team": "CHW",
    "age": null,
    "projected_home_runs": 12.399999999999999,
    "projected_obp": 0.337,
    "projected_runs": 53.89999999999999,
    "projected_rbi": 45.199999999999996,
    "projected_stolen_bases": 5.699999999999999,
    "projected_wins": null,
    "projected_quality_starts": null,
    "projected_strikeouts": null,
    "projected_era": null,
    "projected_whip": null,
    "projected_saves": null,
    "projected_holds": null,
    "drafted": false,
    "drafted_by_team": null,
    "draft_round": null,
    "draft_pick": null,
    "adp": 184.02
  },
  "pick_info": {
    "pick_number": 232,
    "round": 18,
    "team_name": "Long Balls"
  },
  "position": "C"
}