{
  "player": {
    "player_id": "a6132d15-7203-4414-9249-feac9f03f53b",
    "name": "Tatsuya Imai",
    "position": "P",
    "team": "",
    "age": null,
    "projected_home_runs": null,
    "projected_obp": null,
    "projected_runs": null,
    "projected_rbi": null,
    "projected_stolen_bases": null,
    "projected_wins": 8.0,
    "projected_quality_starts": 11.700000000000001,
    "projected_strikeouts": 138.03613333333334,
    "projected_era": 4.29,
    "projected_whip": null,
    "projected_saves": 0.0,
    "projected_holds": null,
    "drafted": false,
    "drafted_by_team": null,
    "draft_round": null,
    "draft_pick": null,
    "adp": 191.8
  },
  "pick_info": {
    "pick_number": 217,
    "round": 17,
    "team_name": "Rieken Havoc"
  },
  "position": "P"
}