{
  "player": {
    "player_id": "a2ef04b3-8ef5-465a-9b59-3efda89f34e6",
    "name": "Anthony Volpe",
    "position": "SS",
    "team": "NYY",
    "age": null,
    "projected_home_runs": 14.7,
    "projected_obp": 0.299,
    "projected_runs": 55.199999999999996,
    "projected_rbi": 53.2,
    "projected_stolen_bases": 17.4,
    "projected_wins": null,
    "projected_quality_starts": null,
    "projected_strikeouts": null,
    "projected_era": null,
    "projected_whip": null,
    "projected_saves": null,
    "projected_holds": null,
    "drafted": false,
    "drafted_by_team": null,
    "draft_round": null,
    "draft_pick": null,
    "adp": 419.78
  },
  "pick_info": {
    "pick_number": 220,
    "round": 17,
    "team_name": "Big Sticks"
  },
  "position": "SS"
}