{
  "player": {
    "player_id": "655c6207-2e20-444b-81e0-5adcd7dabbe9",
    "name": "Royce Lewis",
    "position": "3B",
    "team": "MIN",
    "age": null,
    "projected_home_runs": 23.5,
    "projected_obp": 0.311,
    "projected_runs": 63.7,
    "projected_rbi": 72.1,
    "projected_stolen_bases": 10.399999999999999,
    "projected_wins": null,
    "projected_quality_starts": null,
    "projected_strikeouts": null,
    "projected_era": null,
    "projected_whip": null,
    "projected_saves": null,
    "projected_holds": null,
    "drafted": false,
    "drafted_by_team": null,
    "draft_round": null,
    "draft_pick": null,
    "adp": 198.38
  },
  "pick_info": {
    "pick_number": 207,
    "round": 16,
    "team_name": "Dawg"
  },
  "position": "3B"
}